html2tei/__init__.py
html2tei/__main__.py
html2tei/article_body_converters/__init__.py
html2tei/article_body_converters/eltedh_abc.py
html2tei/article_body_converters/justext_abc.py
html2tei/article_body_converters/newspaper_abc.py
html2tei/basic_tag_dicts.py
html2tei/digest.py
html2tei/excluded_tags_collection.py
html2tei/html_content_tree.py
html2tei/link_corrector.py
html2tei/portal_article_cleaner.py
html2tei/processing_utils.py
html2tei/read_config.py
html2tei/tag_bigrams_maker.py
html2tei/tag_inventory_maker.py
html2tei/tei_utils.py
html2tei/unicode_error.py
html2tei/update_and_filter_tables.py
html2tei/validate_hash_zip.py
html2tei/version.py
html2tei-1.2.3.dist-info/entry_points.txt
html2tei-1.2.3.dist-info/LICENSE
html2tei-1.2.3.dist-info/WHEEL
html2tei-1.2.3.dist-info/METADATA
html2tei-1.2.3.dist-info/RECORD
