Metadata-Version: 2.1
Name: html2tei
Version: 1.2.3
Summary: Map the HTML schema of portals to valid TEI XML with the tags and structures used in them using small manual portal-specific configurations.
Home-page: https://github.com/ELTE-DH/HTML2TEI
License: LGPLv3
Author: dlazesz
Requires-Python: >=3.8,<4.0
Classifier: Development Status :: 5 - Production/Stable
Classifier: License :: Other/Proprietary License
Classifier: Operating System :: OS Independent
Classifier: Programming Language :: Python :: 3
Classifier: Programming Language :: Python :: 3.10
Classifier: Programming Language :: Python :: 3.8
Classifier: Programming Language :: Python :: 3.9
Classifier: Topic :: Software Development :: Libraries :: Python Modules
Provides-Extra: full
Provides-Extra: justext
Provides-Extra: newspaper3k
Requires-Dist: beautifulsoup4 (>=4.9.0,<5.0.0)
Requires-Dist: justext (>=3.0.0,<4.0.0); extra == "justext" or extra == "full"
Requires-Dist: lxml (>=4.5.0,<5.0.0)
Requires-Dist: newspaper3k (>=0.2.8,<0.3.0); extra == "newspaper3k" or extra == "full"
Requires-Dist: pyyaml (>=6.0.0,<7.0.0)
Requires-Dist: warcio (>=1.7.0,<2.0.0)
Requires-Dist: webarticlecurator (>=1.4.0,<2.0.0)
Project-URL: Repository, https://github.com/ELTE-DH/HTML2TEI
